z3c.schema-2.0-py3.11-nspkg.pth
z3c/schema/README.txt
z3c/schema/__init__.py
z3c/schema/baseurl/README.txt
z3c/schema/baseurl/__init__.py
z3c/schema/baseurl/field.py
z3c/schema/baseurl/interfaces.py
z3c/schema/baseurl/tests.py
z3c/schema/dateselect/README.txt
z3c/schema/dateselect/__init__.py
z3c/schema/dateselect/field.py
z3c/schema/dateselect/interfaces.py
z3c/schema/dateselect/tests.py
z3c/schema/email/README.txt
z3c/schema/email/__init__.py
z3c/schema/email/field.py
z3c/schema/email/interfaces.py
z3c/schema/email/tests.py
z3c/schema/hostname/README.txt
z3c/schema/hostname/__init__.py
z3c/schema/hostname/field.py
z3c/schema/hostname/interfaces.py
z3c/schema/hostname/tests.py
z3c/schema/i18n/__init__.py
z3c/schema/i18n/configure.zcml
z3c/schema/i18n/locales/z3c.schema.pot
z3c/schema/i18n/locales/de/LC_MESSAGES/z3c.schema.po
z3c/schema/i18n/locales/fr/LC_MESSAGES/z3c.schema.po
z3c/schema/i18n/locales/nl/LC_MESSAGES/z3c.schema.po
z3c/schema/i18n/locales/ru/LC_MESSAGES/z3c.schema.po
z3c/schema/ip/README.txt
z3c/schema/ip/__init__.py
z3c/schema/ip/field.py
z3c/schema/ip/interfaces.py
z3c/schema/ip/tests.py
z3c/schema/optchoice/README.txt
z3c/schema/optchoice/__init__.py
z3c/schema/optchoice/field.py
z3c/schema/optchoice/interfaces.py
z3c/schema/optchoice/tests.py
z3c/schema/payments/README.txt
z3c/schema/payments/__init__.py
z3c/schema/payments/field.py
z3c/schema/payments/interfaces.py
z3c/schema/payments/tests.py
z3c/schema/regex/README.txt
z3c/schema/regex/__init__.py
z3c/schema/regex/field.py
z3c/schema/regex/interfaces.py
z3c/schema/regex/tests.py
z3c.schema-2.0.dist-info/LICENSE.txt
z3c.schema-2.0.dist-info/METADATA
z3c.schema-2.0.dist-info/WHEEL
z3c.schema-2.0.dist-info/namespace_packages.txt
z3c.schema-2.0.dist-info/top_level.txt
z3c.schema-2.0.dist-info/RECORD
